[
{
  "meteor" : "MTG320",
  "version":2,
  "info" : {
     "title":"JSON pour BDClimato",
     "time":"17/05/2021 à 08h55",
     "uptime":"6 jours, 9 heures, 48 minutes",
     "last_update":"2021-05-17 08:55:00",
     "last_update_before_stop":"2021-05-10 23:05:00" 
     },
  "data":
     [
      {
       "start_dat":"2021-05-17T08:50:00",
       "stop_dat":"2021-05-17T08:55:00",
       "current": {
       "out_temp":23.6666666667,
       "out_temp_min":23.5555555556,       
       "out_temp_min_time":"2021-05-17T08:50:01",
       "out_temp_avg":23.6228844739,
       "out_temp_max":23.6666666667,       
       "out_temp_max_time":"2021-05-17T08:53:05",
       "windchill":23.6666666667,
       "windchill_min":23.5555555556,       
       "windchill_min_time":"2021-05-17T08:50:01",
       "windchill_avg":23.6228844739,
       "heatindex":23.6666666667,
       "heatindex_max":23.6666666667,       
       "heatindex_max_time":"2021-05-17T08:53:05",
       "heatindex_avg":23.6228844739,
       "dewpoint":19.8020177379,
       "dewpoint_min":19.6941675031,       
       "dewpoint_min_time":"2021-05-17T08:50:01",
       "dewpoint_avg":19.7595205464,
       "dewpoint_max":19.8020177379,       
       "dewpoint_max_time":"2021-05-17T08:53:05",
       "humidity":79.0,
       "humidity_min":79.0,       
       "humidity_min_time":"2021-05-17T08:50:01",
       "humidity_avg":79.0,
       "humidity_max":79.0,       
       "humidity_max_time":"2021-05-17T08:50:01",
       "barometer":1018.32078324,
       "barometer_min":1018.25305547,       
       "barometer_min_time":"2021-05-17T08:52:01",
       "barometer_avg":1018.31383105,
       "barometer_max":1018.388511,       
       "barometer_max_time":"2021-05-17T08:51:01",
       "pressure":982.074827509,
       "pressure_min":981.942329635,       
       "pressure_min_time":"2021-05-17T08:52:01",
       "pressure_avg":982.024373464,
       "pressure_max":982.074827509,       
       "pressure_max_time":"2021-05-17T08:53:05",
       "wind_avg":11.2654360001,
       "wind_dir":112.5,
       "gust":24.1402200001,
       "gust_dir":90.0,
       "wind_max":24.1402200001,
       "wind_max_dir":104.0,        
       "wind_max_time":"2021-05-17T08:51:23",    
       "wind10_avg":12.2353079736,
       "rain":0.0,
       "rain_rate":0.0,
       "rain_rate_max_time":"2021-05-17T08:50:01", 
       "rain_rate_avg":0.0,
       "radiation_min":0.355495041431,
       "radiation_min_time":"2021-05-17T08:50:01",
       "radiation":10.9327953832,
       "radiation_max":0.373428593096,
       "radiation_max_time":"2021-05-17T08:54:59",
       "in_temp":24.9444444444,
       "in_temp_max":24.9444444444,
       "in_temp_max_time":"2021-05-17T08:50:01",
       "in_temp_avg":24.9444444444,
       "in_temp_min":24.9444444444,
       "in_temp_min_time":"2021-05-17T08:50:01",
       "in_humidity":63.0,
       "in_humidity_max":63.0,
       "in_humidity_max_time":"2021-05-17T08:50:01",
       "in_humidity_avg":63.0,
       "in_humidity_min":63.0,
       "in_humidity_min_time":"2021-05-17T08:50:01",
       "rx":99.9375,
       "voltage":4.59,
       "voltage_avg":4.59,
       "voltage_min":4.59,
       "voltage_min_time":"2021-05-17T08:50:01",
       "duration":5.0
       }
     }
   ]
}
]
