[
{
  "meteor" : "MTG320",
  "version":2,
  "info" : {
     "title":"JSON pour BDClimato",
     "time":"29/04/2021 à 15h10",
     "uptime":"3 jours, 3 heures, 9 minutes",
     "last_update":"2021-04-29 15:10:00",
     "last_update_before_stop":"2021-04-26 11:45:00" 
     },
  "data":
     [
      {
       "start_dat":"2021-04-29T15:05:00",
       "stop_dat":"2021-04-29T15:10:00",
       "current": {
       "out_temp":25.2222222222,
       "out_temp_min":25.1111111111,       
       "out_temp_min_time":"2021-04-29T15:05:02",
       "out_temp_avg":25.1795437822,
       "out_temp_max":25.2222222222,       
       "out_temp_max_time":"2021-04-29T15:07:48",
       "windchill":25.2222222222,
       "windchill_min":25.1111111111,       
       "windchill_min_time":"2021-04-29T15:05:02",
       "windchill_avg":25.1795437822,
       "heatindex":25.2222222222,
       "heatindex_max":25.2222222222,       
       "heatindex_max_time":"2021-04-29T15:07:48",
       "heatindex_avg":25.1795437822,
       "dewpoint":22.5136538127,
       "dewpoint_min":22.4592368856,       
       "dewpoint_min_time":"2021-04-29T15:07:04",
       "dewpoint_avg":22.5510761143,
       "dewpoint_max":22.6522193513,       
       "dewpoint_max_time":"2021-04-29T15:05:14",
       "humidity":85.0,
       "humidity_min":85.0,       
       "humidity_min_time":"2021-04-29T15:07:04",
       "humidity_avg":85.4105960265,
       "humidity_max":86.0,       
       "humidity_max_time":"2021-04-29T15:05:02",
       "barometer":1015.40848942,
       "barometer_min":1015.37462554,       
       "barometer_min_time":"2021-04-29T15:06:02",
       "barometer_avg":1015.42934598,
       "barometer_max":1015.51008107,       
       "barometer_max_time":"2021-04-29T15:05:02",
       "pressure":979.38831115,
       "pressure_avg":979.409264278,
       "wind_avg":12.8747840001,
       "wind_dir":135.0,
       "windgust":30.5776120002,
       "windgust_dir":67.5,
       "wind_max":30.5776120002,
       "wind_max_dir":116.0,        
       "wind_max_time":"2021-04-29T15:08:30",    
       "wind10_avg":14.4841320001,
       "rain":0.0,
       "rain_rate":0.0,
       "rain_rate_max_time":"2021-04-29T15:05:02", 
       "radiation_min":0.0521440114473,
       "radiation_min_time":"2021-04-29T15:10:00",
       "radiation":15.9003233714,
       "radiation_max":0.053842156438,
       "radiation_max_time":"2021-04-29T15:05:02",
       "in_temp":26.7222222222,
       "in_temp_max":26.7222222222,
       "in_temp_max_time":"2021-04-29T15:05:02",
       "in_temp_avg":26.7222222222,
       "in_temp_min":26.7222222222,
       "in_temp_min_time":"2021-04-29T15:05:02",
       "in_humidity":72.0,
       "in_humidity_max":72.0,
       "in_humidity_max_time":"2021-04-29T15:05:02",
       "in_humidity_avg":72.0,
       "in_humidity_min":72.0,
       "in_humidity_min_time":"2021-04-29T15:05:02",
       "rx":99.9375,
       "voltage":4.59,
       "duration":5.0
       }
     }
   ]
}
]
