[
{
  "meteor" : "MTG320",
  "version":2,
  "info" : {
     "title":"JSON pour BDClimato",
     "hardware":"Vantage Pro2",
     "weewxVersion":"3.9.2",
     "time":"04/01/2022 à 06h30",
     "uptime":"0 jours, 10 heures, 14 minutes",
     "last_update":"2022-01-04 06:30:00",
     "last_update_before_stop":"2022-01-03 20:15:00" 
     },
  "data":
     [
      {
       "start_dat":"2022-01-04T06:25:00",
       "stop_dat":"2022-01-04T06:30:00",
       "current": {
       "out_temp":22.5,
       "out_temp_min":22.5,       
       "out_temp_min_time":"2022-01-04T06:25:20",
       "out_temp_avg":22.5397350993,
       "out_temp_max":22.5555555556,       
       "out_temp_max_time":"2022-01-04T06:25:02",
       "windchill":22.5,
       "windchill_min":22.5,       
       "windchill_min_time":"2022-01-04T06:25:20",
       "windchill_avg":22.5397350993,
       "heatindex":22.5,
       "heatindex_max":22.5555555556,       
       "heatindex_max_time":"2022-01-04T06:25:02",
       "heatindex_avg":22.5397350993,
       "dewpoint":20.4086220325,
       "dewpoint_min":20.4086220325,       
       "dewpoint_min_time":"2022-01-04T06:26:18",
       "dewpoint_avg":20.495130218,
       "dewpoint_max":20.6468731586,       
       "dewpoint_max_time":"2022-01-04T06:25:02",
       "humidity":88.0,
       "humidity_min":88.0,       
       "humidity_min_time":"2022-01-04T06:26:18",
       "humidity_avg":88.2582781457,
       "humidity_max":89.0,       
       "humidity_max_time":"2022-01-04T06:25:02",
       "barometer":1014.32484521,
       "barometer_min":1014.18938968,       
       "barometer_min_time":"2022-01-04T06:26:00",
       "barometer_avg":1014.29120559,
       "barometer_max":1014.32484521,       
       "barometer_max_time":"2022-01-04T06:25:02",
       "pressure":978.233037329,
       "pressure_min":978.102401595,       
       "pressure_min_time":"2022-01-04T06:26:18",
       "pressure_avg":978.202334866,
       "pressure_max":978.237837877,       
       "pressure_max_time":"2022-01-04T06:25:02",
       "wind_avg":1.78816444589,
       "wind_dir":135.0,
       "wind_max":4.47041111472,
       "wind_max_dir":90.0,
       "wind_max_time":"2022-01-04T06:29:52",    
       "wind10_avg":1.96579667561,
       "rain":0.0,
       "rain_rate_max":0.0,
       "rain_rate_max_time":"2022-01-04T06:25:02", 
       "rain_rate_avg":0.0,
       "in_temp":25.3888888889,
       "in_temp_max":25.3888888889,
       "in_temp_max_time":"2022-01-04T06:25:02",
       "in_temp_avg":25.3888888889,
       "in_temp_min":25.3888888889,
       "in_temp_min_time":"2022-01-04T06:25:02",
       "in_humidity":68.0,
       "in_humidity_max":68.0,
       "in_humidity_max_time":"2022-01-04T06:25:02",
       "in_humidity_avg":68.0,
       "in_humidity_min":68.0,
       "in_humidity_min_time":"2022-01-04T06:25:02",
       "rx":99.0833333333,
       "voltage":4.58,
       "voltage_avg":4.58,
       "voltage_min":4.58,
       "voltage_min_time":"2022-01-04T06:25:02",
       "duration":5.0
       }
     }
   ]
}
]
