[
{
  "meteor" : "MTG320",
  "version":2,
  "info" : {
     "title":"JSON pour BDClimato",
     "hardware":"Vantage Pro2",
     "weewxVersion":"3.9.1-1",
     "time":"31/01/2022 à 01h05",
     "uptime":"23 jours, 15 heures, 23 minutes",
     "last_update":"2022-01-31 01:05:00",
     "last_update_before_stop":"2022-01-07 09:40:00" 
     },
  "data":
     [
      {
       "start_dat":"2022-01-31T01:00:00",
       "stop_dat":"2022-01-31T01:05:00",
       "current": {
       "out_temp":23.4444444444,
       "out_temp_min":23.3888888889,       
       "out_temp_min_time":"2022-01-31T01:00:14",
       "out_temp_avg":23.4400294334,
       "out_temp_max":23.5,       
       "out_temp_max_time":"2022-01-31T01:04:08",
       "windchill":23.4444444444,
       "windchill_min":23.3888888889,       
       "windchill_min_time":"2022-01-31T01:00:14",
       "windchill_avg":23.4400294334,
       "heatindex":23.4444444444,
       "heatindex_max":23.5,       
       "heatindex_max_time":"2022-01-31T01:04:08",
       "heatindex_avg":23.4400294334,
       "dewpoint":21.3379182864,
       "dewpoint_min":21.2832553018,       
       "dewpoint_min_time":"2022-01-31T01:00:14",
       "dewpoint_avg":21.3335741833,
       "dewpoint_max":21.3925810834,       
       "dewpoint_max_time":"2022-01-31T01:04:08",
       "humidity":88.0,
       "humidity_min":88.0,       
       "humidity_min_time":"2022-01-31T01:00:02",
       "humidity_avg":88.0,
       "humidity_max":88.0,       
       "humidity_max_time":"2022-01-31T01:00:02",
       "barometer":1010.59981824,
       "barometer_min":1010.59981824,       
       "barometer_min_time":"2022-01-31T01:02:00",
       "barometer_avg":1010.63345785,
       "barometer_max":1010.70140988,       
       "barometer_max_time":"2022-01-31T01:01:00",
       "pressure":974.919279865,
       "pressure_min":974.919279865,       
       "pressure_min_time":"2022-01-31T01:02:00",
       "pressure_avg":974.951642534,
       "pressure_max":975.017284685,       
       "pressure_max_time":"2022-01-31T01:01:04",
       "wind_avg":1.78816444589,
       "wind_dir":135.0,
       "wind_max":3.57632889177,
       "wind_max_dir":135.0,
       "wind_max_time":"2022-01-31T01:02:34",    
       "wind10_avg":1.78520390872,
       "rain":0.0,
       "rain_rate_max":0.0,
       "rain_rate_max_time":"2022-01-31T01:00:02", 
       "rain_rate_avg":0.0,
       "in_temp":27.5555555556,
       "in_temp_max":27.5555555556,
       "in_temp_max_time":"2022-01-31T01:00:02",
       "in_temp_avg":27.555187638,
       "in_temp_min":27.5,
       "in_temp_min_time":"2022-01-31T01:05:00",
       "in_humidity":68.0,
       "in_humidity_max":68.0,
       "in_humidity_max_time":"2022-01-31T01:00:02",
       "in_humidity_avg":68.0,
       "in_humidity_min":68.0,
       "in_humidity_min_time":"2022-01-31T01:00:02",
       "rx":100.0,
       "voltage":4.58,
       "voltage_avg":4.58,
       "voltage_min":4.58,
       "voltage_min_time":"2022-01-31T01:00:02",
       "duration":5.0
       }
     }
   ]
}
]
