[
{
  "meteor" : "MTG320",
  "version":2,
  "info" : {
     "title":"JSON pour BDClimato",
     "hardware":"Vantage Pro2",
     "weewxVersion":"3.9.1-1",
     "time":"23/01/2022 à 15h35",
     "uptime":"16 jours, 5 heures, 53 minutes",
     "last_update":"2022-01-23 15:35:00",
     "last_update_before_stop":"2022-01-07 09:40:00" 
     },
  "data":
     [
      {
       "start_dat":"2022-01-23T15:30:00",
       "stop_dat":"2022-01-23T15:35:00",
       "current": {
       "out_temp":29.1111111111,
       "out_temp_min":29.0555555556,       
       "out_temp_min_time":"2022-01-23T15:31:22",
       "out_temp_avg":29.0864606328,
       "out_temp_max":29.1666666667,       
       "out_temp_max_time":"2022-01-23T15:30:02",
       "windchill":29.1111111111,
       "windchill_min":29.0555555556,       
       "windchill_min_time":"2022-01-23T15:31:22",
       "windchill_avg":29.0864606328,
       "heatindex":35.9776068413,
       "heatindex_max":36.2171937596,       
       "heatindex_max_time":"2022-01-23T15:33:32",
       "heatindex_avg":35.7761687987,
       "dewpoint":26.1214437268,
       "dewpoint_min":25.7135006925,       
       "dewpoint_min_time":"2022-01-23T15:30:30",
       "dewpoint_avg":25.9877560123,
       "dewpoint_max":26.3222500855,       
       "dewpoint_max_time":"2022-01-23T15:33:32",
       "humidity":84.0,
       "humidity_min":82.0,       
       "humidity_min_time":"2022-01-23T15:30:06",
       "humidity_avg":83.4635761589,
       "humidity_max":85.0,       
       "humidity_max_time":"2022-01-23T15:33:32",
       "barometer":1010.87072929,
       "barometer_min":1010.76913764,       
       "barometer_min_time":"2022-01-23T15:35:00",
       "barometer_avg":1010.89696819,
       "barometer_max":1010.97232093,       
       "barometer_max_time":"2022-01-23T15:30:02",
       "pressure":975.484079519,
       "pressure_min":975.386044202,       
       "pressure_min_time":"2022-01-23T15:35:00",
       "pressure_avg":975.505943312,
       "pressure_max":975.578252293,       
       "pressure_max_time":"2022-01-23T15:30:02",
       "wind_avg":1.78816444589,
       "wind_dir":90.0,
       "wind_max":4.91745222619,
       "wind_max_dir":90.0,
       "wind_max_time":"2022-01-23T15:30:02",    
       "wind10_avg":2.1463894425,
       "rain":0.0,
       "rain_rate_max":0.0,
       "rain_rate_max_time":"2022-01-23T15:30:02", 
       "rain_rate_avg":0.0,
       "in_temp":30.5555555556,
       "in_temp_max":30.5555555556,
       "in_temp_max_time":"2022-01-23T15:30:02",
       "in_temp_avg":30.5555555556,
       "in_temp_min":30.5555555556,
       "in_temp_min_time":"2022-01-23T15:30:02",
       "in_humidity":71.0,
       "in_humidity_max":71.0,
       "in_humidity_max_time":"2022-01-23T15:30:02",
       "in_humidity_avg":71.0,
       "in_humidity_min":71.0,
       "in_humidity_min_time":"2022-01-23T15:30:02",
       "rx":99.9375,
       "voltage":4.58,
       "voltage_avg":4.58,
       "voltage_min":4.58,
       "voltage_min_time":"2022-01-23T15:30:02",
       "duration":5.0
       }
     }
   ]
}
]
