[
{
  "meteor" : "MTG320",
  "version":2,
  "info" : {
     "title":"JSON pour BDClimato",
     "hardware":"Vantage Pro2",
     "weewxVersion":"3.9.1-1",
     "time":"12/01/2022 à 08h05",
     "uptime":"4 jours, 22 heures, 23 minutes",
     "last_update":"2022-01-12 08:05:00",
     "last_update_before_stop":"2022-01-07 09:40:00" 
     },
  "data":
     [
      {
       "start_dat":"2022-01-12T08:00:00",
       "stop_dat":"2022-01-12T08:05:00",
       "current": {
       "out_temp":24.6666666667,
       "out_temp_min":24.6666666667,       
       "out_temp_min_time":"2022-01-12T08:03:09",
       "out_temp_avg":24.7016188374,
       "out_temp_max":24.7222222222,       
       "out_temp_max_time":"2022-01-12T08:00:01",
       "windchill":24.6666666667,
       "windchill_min":24.6666666667,       
       "windchill_min_time":"2022-01-12T08:03:09",
       "windchill_avg":24.7016188374,
       "heatindex":24.6666666667,
       "heatindex_max":24.7222222222,       
       "heatindex_max_time":"2022-01-12T08:00:01",
       "heatindex_avg":24.7016188374,
       "dewpoint":22.7270088089,
       "dewpoint_min":22.7270088089,       
       "dewpoint_min_time":"2022-01-12T08:03:09",
       "dewpoint_avg":22.7614460382,
       "dewpoint_max":22.7817458787,       
       "dewpoint_max_time":"2022-01-12T08:00:01",
       "humidity":89.0,
       "humidity_min":89.0,       
       "humidity_min_time":"2022-01-12T08:00:01",
       "humidity_avg":89.0,
       "humidity_max":89.0,       
       "humidity_max_time":"2022-01-12T08:00:01",
       "barometer":1015.13757837,
       "barometer_min":1015.03598672,       
       "barometer_min_time":"2022-01-12T08:00:59",
       "barometer_avg":1015.09743509,
       "barometer_max":1015.17144225,       
       "barometer_max_time":"2022-01-12T08:04:59",
       "pressure":979.261984748,
       "pressure_min":979.165211504,       
       "pressure_min_time":"2022-01-12T08:00:59",
       "pressure_avg":979.224032827,
       "pressure_max":979.294651859,       
       "pressure_max_time":"2022-01-12T08:04:59",
       "wind_avg":3.1292877803,
       "wind_dir":90.0,
       "wind_max":6.70561667207,
       "wind_max_dir":90.0,
       "wind_max_time":"2022-01-12T08:00:01",    
       "wind10_avg":3.66514500663,
       "rain":0.0,
       "rain_rate_max":0.0,
       "rain_rate_max_time":"2022-01-12T08:00:01", 
       "rain_rate_avg":0.0,
       "in_temp":26.5,
       "in_temp_max":26.5555555556,
       "in_temp_max_time":"2022-01-12T08:00:01",
       "in_temp_avg":26.5334805004,
       "in_temp_min":26.5,
       "in_temp_min_time":"2022-01-12T08:01:59",
       "in_humidity":71.0,
       "in_humidity_max":71.0,
       "in_humidity_max_time":"2022-01-12T08:00:01",
       "in_humidity_avg":71.0,
       "in_humidity_min":71.0,
       "in_humidity_min_time":"2022-01-12T08:00:01",
       "rx":99.0833333333,
       "voltage":4.58,
       "voltage_avg":4.58,
       "voltage_min":4.58,
       "voltage_min_time":"2022-01-12T08:00:01",
       "duration":5.0
       }
     }
   ]
}
]
