[
{
  "meteor" : "MTG320",
  "version":2,
  "info" : {
     "title":"JSON pour BDClimato",
     "hardware":"Vantage Pro2",
     "weewxVersion":"3.9.2",
     "time":"26/12/2021 à 08h25",
     "uptime":"6 jours, 0 heures, 32 minutes",
     "last_update":"2021-12-26 08:25:00",
     "last_update_before_stop":"2021-12-20 07:10:00" 
     },
  "data":
     [
      {
       "start_dat":"2021-12-26T08:20:00",
       "stop_dat":"2021-12-26T08:25:00",
       "current": {
       "out_temp":26.8333333333,
       "out_temp_min":26.7222222222,       
       "out_temp_min_time":"2021-12-26T08:20:01",
       "out_temp_avg":26.7899190581,
       "out_temp_max":26.8333333333,       
       "out_temp_max_time":"2021-12-26T08:22:59",
       "windchill":26.8333333333,
       "windchill_min":26.7222222222,       
       "windchill_min_time":"2021-12-26T08:20:01",
       "windchill_avg":26.7899190581,
       "heatindex":29.7191502406,
       "heatindex_max":29.8075966016,       
       "heatindex_max_time":"2021-12-26T08:22:59",
       "heatindex_avg":29.6438371187,
       "dewpoint":23.8942127397,
       "dewpoint_min":23.7855564247,       
       "dewpoint_min_time":"2021-12-26T08:20:01",
       "dewpoint_avg":23.9184134315,
       "dewpoint_max":24.0916416502,       
       "dewpoint_max_time":"2021-12-26T08:22:59",
       "humidity":84.0,
       "humidity_min":84.0,       
       "humidity_min_time":"2021-12-26T08:20:01",
       "humidity_avg":84.3377483444,
       "humidity_max":85.0,       
       "humidity_max_time":"2021-12-26T08:21:25",
       "barometer":1014.49416462,
       "barometer_min":1014.49416462,       
       "barometer_min_time":"2021-12-26T08:24:01",
       "barometer_avg":1014.54193288,
       "barometer_max":1014.59575626,       
       "barometer_max_time":"2021-12-26T08:20:01",
       "pressure":978.79729621,
       "pressure_min":978.79729621,       
       "pressure_min_time":"2021-12-26T08:24:01",
       "pressure_avg":978.843957947,
       "pressure_max":978.894031764,       
       "pressure_max_time":"2021-12-26T08:20:35",
       "wind_avg":0.447041111472,
       "wind_dir":0.0,
       "wind_max":1.78816444589,
       "wind_max_dir":0.0,
       "wind_max_time":"2021-12-26T08:20:01",    
       "wind10_avg":0.894082222943,
       "rain":0.0,
       "rain_rate_max":0.0,
       "rain_rate_max_time":"2021-12-26T08:20:01", 
       "rain_rate_avg":0.0,
       "in_temp":27.8333333333,
       "in_temp_max":27.8888888889,
       "in_temp_max_time":"2021-12-26T08:23:01",
       "in_temp_avg":27.8443708609,
       "in_temp_min":27.8333333333,
       "in_temp_min_time":"2021-12-26T08:20:01",
       "in_humidity":69.0,
       "in_humidity_max":69.0,
       "in_humidity_max_time":"2021-12-26T08:20:01",
       "in_humidity_avg":69.0,
       "in_humidity_min":69.0,
       "in_humidity_min_time":"2021-12-26T08:20:01",
       "rx":99.9375,
       "voltage":4.58,
       "voltage_avg":4.58,
       "voltage_min":4.58,
       "voltage_min_time":"2021-12-26T08:20:01",
       "duration":5.0
       }
     }
   ]
}
]
