[
{
  "meteor" : "MTG320",
  "version":2,
  "info" : {
     "title":"JSON pour BDClimato",
     "time":"09/05/2021 à 04h25",
     "uptime":"0 jours, 6 heures, 0 minutes",
     "last_update":"2021-05-09 04:25:00",
     "last_update_before_stop":"2021-05-08 22:20:00" 
     },
  "data":
     [
      {
       "start_dat":"2021-05-09T04:20:00",
       "stop_dat":"2021-05-09T04:25:00",
       "current": {
       "out_temp":18.5555555556,
       "out_temp_min":18.5555555556,       
       "out_temp_min_time":"2021-05-09T04:20:02",
       "out_temp_avg":18.5577630611,
       "out_temp_max":18.6111111111,       
       "out_temp_max_time":"2021-05-09T04:24:26",
       "windchill":18.5555555556,
       "windchill_min":18.5555555556,       
       "windchill_min_time":"2021-05-09T04:20:02",
       "windchill_avg":18.5577630611,
       "heatindex":18.5555555556,
       "heatindex_max":18.6111111111,       
       "heatindex_max_time":"2021-05-09T04:24:26",
       "heatindex_avg":18.5577630611,
       "dewpoint":15.2285198937,
       "dewpoint_min":15.2285198937,       
       "dewpoint_min_time":"2021-05-09T04:20:02",
       "dewpoint_avg":15.230670444,
       "dewpoint_max":15.2826420758,       
       "dewpoint_max_time":"2021-05-09T04:24:26",
       "humidity":81.0,
       "humidity_min":81.0,       
       "humidity_min_time":"2021-05-09T04:20:02",
       "humidity_avg":81.0,
       "humidity_max":81.0,       
       "humidity_max_time":"2021-05-09T04:20:02",
       "barometer":1013.34279264,
       "barometer_min":1013.30892876,       
       "barometer_min_time":"2021-05-09T04:21:00",
       "barometer_avg":1013.376208,
       "barometer_max":1013.44438429,       
       "barometer_max_time":"2021-05-09T04:23:00",
       "pressure":976.92958104,
       "pressure_min":976.896934015,       
       "pressure_min_time":"2021-05-09T04:21:00",
       "pressure_avg":976.961828696,
       "pressure_max":977.027522115,       
       "pressure_max_time":"2021-05-09T04:23:00",
       "wind_avg":12.8747840001,
       "wind_dir":135.0,
       "windgust":16.0934800001,
       "windgust_dir":135.0,
       "wind_max":16.0934800001,
       "wind_max_dir":171.0,        
       "wind_max_time":"2021-05-09T04:23:00",    
       "wind10_avg":11.2654360001,
       "rain":0.0,
       "rain_rate":0.0,
       "rain_rate_max_time":"2021-05-09T04:20:02", 
       "rain_rate_avg":0.0,
       "radiation_min":0.0,
       "radiation_min_time":"2021-05-09T04:20:02",
       "radiation":0.0,
       "radiation_max":0.0,
       "radiation_max_time":"2021-05-09T04:20:02",
       "in_temp":23.3888888889,
       "in_temp_max":23.4444444444,
       "in_temp_max_time":"2021-05-09T04:20:02",
       "in_temp_avg":23.3999264165,
       "in_temp_min":23.3888888889,
       "in_temp_min_time":"2021-05-09T04:21:00",
       "in_humidity":62.0,
       "in_humidity_max":62.0,
       "in_humidity_max_time":"2021-05-09T04:20:02",
       "in_humidity_avg":62.0,
       "in_humidity_min":62.0,
       "in_humidity_min_time":"2021-05-09T04:20:02",
       "rx":99.9375,
       "voltage":4.59,
       "voltage_avg":4.59,
       "voltage_min":4.59,
       "voltage_min_time":"2021-05-09T04:20:02",
       "duration":5.0
       }
     }
   ]
}
]
