[
{
  "meteor" : "MTG320",
  "version":2,
  "info" : {
     "title":"JSON pour BDClimato",
     "time":"30/04/2021 à 05h35",
     "uptime":"3 jours, 17 heures, 34 minutes",
     "last_update":"2021-04-30 05:35:00",
     "last_update_before_stop":"2021-04-26 11:45:00" 
     },
  "data":
     [
      {
       "start_dat":"2021-04-30T05:30:00",
       "stop_dat":"2021-04-30T05:35:00",
       "current": {
       "out_temp":21.0555555556,
       "out_temp_min":21.0555555556,       
       "out_temp_min_time":"2021-04-30T05:30:01",
       "out_temp_avg":21.059602649,
       "out_temp_max":21.1111111111,       
       "out_temp_max_time":"2021-04-30T05:32:33",
       "windchill":21.0555555556,
       "windchill_min":21.0555555556,       
       "windchill_min_time":"2021-04-30T05:30:01",
       "windchill_avg":21.059602649,
       "heatindex":21.0555555556,
       "heatindex_max":21.1111111111,       
       "heatindex_max_time":"2021-04-30T05:32:33",
       "heatindex_avg":21.059602649,
       "dewpoint":19.5264248155,
       "dewpoint_min":19.5264248155,       
       "dewpoint_min_time":"2021-04-30T05:34:03",
       "dewpoint_avg":19.6728504472,
       "dewpoint_max":19.757675768,       
       "dewpoint_max_time":"2021-04-30T05:32:33",
       "humidity":91.0,
       "humidity_min":91.0,       
       "humidity_min_time":"2021-04-30T05:34:03",
       "humidity_avg":91.8079470199,
       "humidity_max":92.0,       
       "humidity_max_time":"2021-04-30T05:30:01",
       "barometer":1015.54394495,
       "barometer_min":1015.27303389,       
       "barometer_min_time":"2021-04-30T05:31:01",
       "barometer_avg":1015.40153723,
       "barometer_max":1015.54394495,       
       "barometer_max_time":"2021-04-30T05:34:01",
       "pressure":979.259267852,
       "pressure_avg":979.124782241,
       "wind_avg":12.8747840001,
       "wind_dir":135.0,
       "windgust":22.5308720001,
       "windgust_dir":67.5,
       "wind_max":25.7495680002,
       "wind_max_dir":153.0,        
       "wind_max_time":"2021-04-30T05:30:01",    
       "wind10_avg":12.5550459868,
       "rain":0.0,
       "rain_rate":1.52399999845,
       "rain_rate_max_time":"2021-04-30T05:30:01", 
       "radiation_min":0.0,
       "radiation_min_time":"2021-04-30T05:30:01",
       "radiation":0.0,
       "radiation_max":0.0,
       "radiation_max_time":"2021-04-30T05:30:01",
       "in_temp":26.9444444444,
       "in_temp_max":26.9444444444,
       "in_temp_max_time":"2021-04-30T05:33:01",
       "in_temp_avg":26.9109639441,
       "in_temp_min":26.8888888889,
       "in_temp_min_time":"2021-04-30T05:30:01",
       "in_humidity":68.0,
       "in_humidity_max":68.0,
       "in_humidity_max_time":"2021-04-30T05:30:01",
       "in_humidity_avg":68.0,
       "in_humidity_min":68.0,
       "in_humidity_min_time":"2021-04-30T05:30:01",
       "rx":99.0833333333,
       "voltage":4.59,
       "duration":5.0
       }
     }
   ]
}
]
