[
{
  "meteor" : "MTG320",
  "version":2,
  "info" : {
     "title":"JSON pour BDClimato",
     "time":"30/04/2021 à 23h20",
     "uptime":"4 jours, 11 heures, 19 minutes",
     "last_update":"2021-04-30 23:20:00",
     "last_update_before_stop":"2021-04-26 11:45:00" 
     },
  "data":
     [
      {
       "start_dat":"2021-04-30T23:15:00",
       "stop_dat":"2021-04-30T23:20:00",
       "current": {
       "out_temp":23.2777777778,
       "out_temp_min":23.2222222222,       
       "out_temp_min_time":"2021-04-30T23:15:01",
       "out_temp_avg":23.2571743929,
       "out_temp_max":23.2777777778,       
       "out_temp_max_time":"2021-04-30T23:15:39",
       "windchill":23.2777777778,
       "windchill_min":23.2222222222,       
       "windchill_min_time":"2021-04-30T23:15:01",
       "windchill_avg":23.2571743929,
       "heatindex":23.2777777778,
       "heatindex_max":23.2777777778,       
       "heatindex_max_time":"2021-04-30T23:15:39",
       "heatindex_avg":23.2571743929,
       "dewpoint":21.3585263638,
       "dewpoint_min":21.1192652223,       
       "dewpoint_min_time":"2021-04-30T23:18:23",
       "dewpoint_avg":21.3076649373,
       "dewpoint_max":21.3585263638,       
       "dewpoint_max_time":"2021-04-30T23:15:39",
       "humidity":89.0,
       "humidity_min":88.0,       
       "humidity_min_time":"2021-04-30T23:18:21",
       "humidity_avg":88.8344370861,
       "humidity_max":89.0,       
       "humidity_max_time":"2021-04-30T23:15:01",
       "barometer":1017.13554738,
       "barometer_min":1017.00009186,       
       "barometer_min_time":"2021-04-30T23:15:03",
       "barometer_avg":1017.10078644,
       "barometer_max":1017.16941126,       
       "barometer_max_time":"2021-04-30T23:17:03",
       "pressure":981.1596903,
       "pressure_avg":981.125100728,
       "wind_avg":9.65608800006,
       "wind_dir":90.0,
       "windgust":24.1402200001,
       "windgust_dir":157.5,
       "wind_max":24.1402200001,
       "wind_max_dir":169.0,        
       "wind_max_time":"2021-04-30T23:15:01",    
       "wind10_avg":9.64543006628,
       "rain":0.0,
       "rain_rate":0.0,
       "rain_rate_max_time":"2021-04-30T23:15:01", 
       "radiation_min":0.0,
       "radiation_min_time":"2021-04-30T23:15:01",
       "radiation":0.0,
       "radiation_max":0.0,
       "radiation_max_time":"2021-04-30T23:15:01",
       "in_temp":26.5555555556,
       "in_temp_max":26.5555555556,
       "in_temp_max_time":"2021-04-30T23:15:03",
       "in_temp_avg":26.555187638,
       "in_temp_min":26.5,
       "in_temp_min_time":"2021-04-30T23:15:01",
       "in_humidity":68.0,
       "in_humidity_max":68.0,
       "in_humidity_max_time":"2021-04-30T23:15:01",
       "in_humidity_avg":68.0,
       "in_humidity_min":68.0,
       "in_humidity_min_time":"2021-04-30T23:15:01",
       "rx":99.9375,
       "voltage":4.59,
       "duration":5.0
       }
     }
   ]
}
]
