[
{
  "meteor" : "MTG320",
  "version":2,
  "info" : {
     "title":"JSON pour BDClimato",
     "time":"26/05/2021 à 02h40",
     "uptime":"7 jours, 15 heures, 34 minutes",
     "last_update":"2021-05-26 02:40:00",
     "last_update_before_stop":"2021-05-18 10:55:00" 
     },
  "data":
     [
      {
       "start_dat":"2021-05-26T02:35:00",
       "stop_dat":"2021-05-26T02:40:00",
       "current": {
       "out_temp":21.1666666667,
       "out_temp_min":21.0555555556,       
       "out_temp_min_time":"2021-05-26T02:35:02",
       "out_temp_avg":21.1136865342,
       "out_temp_max":21.1666666667,       
       "out_temp_max_time":"2021-05-26T02:38:20",
       "windchill":21.1666666667,
       "windchill_min":21.0555555556,       
       "windchill_min_time":"2021-05-26T02:35:02",
       "windchill_avg":21.1136865342,
       "heatindex":21.1666666667,
       "heatindex_max":21.1666666667,       
       "heatindex_max_time":"2021-05-26T02:38:20",
       "heatindex_avg":21.1136865342,
       "dewpoint":17.7719331392,
       "dewpoint_min":17.7178249696,       
       "dewpoint_min_time":"2021-05-26T02:38:38",
       "dewpoint_avg":17.8611906168,
       "dewpoint_max":17.9671622004,       
       "dewpoint_max_time":"2021-05-26T02:38:20",
       "humidity":81.0,
       "humidity_min":81.0,       
       "humidity_min_time":"2021-05-26T02:38:38",
       "humidity_avg":81.7218543046,
       "humidity_max":82.0,       
       "humidity_max_time":"2021-05-26T02:35:02",
       "barometer":1017.60964172,
       "barometer_min":1017.50805008,       
       "barometer_min_time":"2021-05-26T02:40:00",
       "barometer_avg":1017.57532931,
       "barometer_max":1017.64350561,       
       "barometer_max_time":"2021-05-26T02:36:00",
       "pressure":981.351523228,
       "pressure_min":981.253551362,       
       "pressure_min_time":"2021-05-26T02:40:00",
       "pressure_avg":981.319995319,
       "pressure_max":981.386648684,       
       "pressure_max_time":"2021-05-26T02:36:00",
       "wind_avg":11.2654360001,
       "wind_dir":135.0,
       "gust":17.7028280001,
       "gust_dir":157.5,
       "wind_max":22.5308720001,
       "wind_max_dir":167.0,        
       "wind_max_time":"2021-05-26T02:35:02",    
       "wind10_avg":11.9049120266,
       "rain":0.0,
       "rain_rate":0.0,
       "rain_rate_max_time":"2021-05-26T02:35:02", 
       "rain_rate_avg":0.0,
       "radiation_min":0.0,
       "radiation_min_time":"2021-05-26T02:35:02",
       "radiation":0.0,
       "radiation_max":0.0,
       "radiation_max_time":"2021-05-26T02:35:02",
       "in_temp":24.1666666667,
       "in_temp_max":24.2222222222,
       "in_temp_max_time":"2021-05-26T02:35:02",
       "in_temp_avg":24.1777041943,
       "in_temp_min":24.1666666667,
       "in_temp_min_time":"2021-05-26T02:36:00",
       "in_humidity":70.0,
       "in_humidity_max":70.0,
       "in_humidity_max_time":"2021-05-26T02:35:02",
       "in_humidity_avg":70.0,
       "in_humidity_min":70.0,
       "in_humidity_min_time":"2021-05-26T02:35:02",
       "rx":99.9375,
       "voltage":4.59,
       "voltage_avg":4.59,
       "voltage_min":4.59,
       "voltage_min_time":"2021-05-26T02:35:02",
       "duration":5.0
       }
     }
   ]
}
]
