[
{
  "meteor" : "MTG320",
  "version":2,
  "info" : {
     "title":"JSON pour BDClimato",
     "hardware":"Vantage Pro2",
     "weewxVersion":"3.9.2",
     "time":"02/01/2022 à 20h45",
     "uptime":"13 jours, 12 heures, 52 minutes",
     "last_update":"2022-01-02 20:45:00",
     "last_update_before_stop":"2021-12-20 07:10:00" 
     },
  "data":
     [
      {
       "start_dat":"2022-01-02T20:40:00",
       "stop_dat":"2022-01-02T20:45:00",
       "current": {
       "out_temp":22.9444444444,
       "out_temp_min":22.9444444444,       
       "out_temp_min_time":"2022-01-02T20:40:16",
       "out_temp_avg":22.9495952907,
       "out_temp_max":23.0,       
       "out_temp_max_time":"2022-01-02T20:40:01",
       "windchill":22.9444444444,
       "windchill_min":22.9444444444,       
       "windchill_min_time":"2022-01-02T20:40:16",
       "windchill_avg":22.9495952907,
       "heatindex":22.9444444444,
       "heatindex_max":23.0,       
       "heatindex_max_time":"2022-01-02T20:40:01",
       "heatindex_avg":22.9495952907,
       "dewpoint":20.4721307762,
       "dewpoint_min":20.282365522,       
       "dewpoint_min_time":"2022-01-02T20:40:16",
       "dewpoint_avg":20.3716121557,
       "dewpoint_max":20.4721307762,       
       "dewpoint_max_time":"2022-01-02T20:42:47",
       "humidity":86.0,
       "humidity_min":85.0,       
       "humidity_min_time":"2022-01-02T20:40:01",
       "humidity_avg":85.4437086093,
       "humidity_max":86.0,       
       "humidity_max_time":"2022-01-02T20:42:47",
       "barometer":1012.66551501,
       "barometer_min":1012.56392337,       
       "barometer_min_time":"2022-01-02T20:40:01",
       "barometer_avg":1012.61101883,
       "barometer_max":1012.66551501,       
       "barometer_max_time":"2022-01-02T20:44:01",
       "pressure":976.634033226,
       "pressure_min":976.532270586,       
       "pressure_min_time":"2022-01-02T20:40:16",
       "pressure_avg":976.579470519,
       "pressure_max":976.634033226,       
       "pressure_max_time":"2022-01-02T20:44:01",
       "wind_avg":4.02337000324,
       "wind_dir":112.5,
       "wind_max":6.2585755606,
       "wind_max_dir":67.5,
       "wind_max_time":"2022-01-02T20:40:35",    
       "wind10_avg":3.57632889177,
       "rain":0.0,
       "rain_rate_max":0.0,
       "rain_rate_max_time":"2022-01-02T20:40:01", 
       "rain_rate_avg":0.0,
       "in_temp":26.5555555556,
       "in_temp_max":26.5555555556,
       "in_temp_max_time":"2022-01-02T20:40:01",
       "in_temp_avg":26.5555555556,
       "in_temp_min":26.5555555556,
       "in_temp_min_time":"2022-01-02T20:40:01",
       "in_humidity":66.0,
       "in_humidity_max":66.0,
       "in_humidity_max_time":"2022-01-02T20:40:01",
       "in_humidity_avg":65.8013245033,
       "in_humidity_min":65.0,
       "in_humidity_min_time":"2022-01-02T20:41:01",
       "rx":100.0,
       "voltage":4.58,
       "voltage_avg":4.58,
       "voltage_min":4.58,
       "voltage_min_time":"2022-01-02T20:40:01",
       "duration":5.0
       }
     }
   ]
}
]
