[
{
  "meteor" : "MTG320",
  "version":2,
  "info" : {
     "title":"JSON pour BDClimato",
     "time":"01/05/2021 à 05h25",
     "uptime":"4 jours, 17 heures, 24 minutes",
     "last_update":"2021-05-01 05:25:00",
     "last_update_before_stop":"2021-04-26 11:45:00" 
     },
  "data":
     [
      {
       "start_dat":"2021-05-01T05:20:00",
       "stop_dat":"2021-05-01T05:25:00",
       "current": {
       "out_temp":22.6111111111,
       "out_temp_min":22.6111111111,       
       "out_temp_min_time":"2021-05-01T05:21:45",
       "out_temp_avg":22.6364974246,
       "out_temp_max":22.7222222222,       
       "out_temp_max_time":"2021-05-01T05:20:13",
       "windchill":22.6111111111,
       "windchill_min":22.6111111111,       
       "windchill_min_time":"2021-05-01T05:21:45",
       "windchill_avg":22.6364974246,
       "heatindex":22.6111111111,
       "heatindex_max":22.7222222222,       
       "heatindex_max_time":"2021-05-01T05:20:13",
       "heatindex_avg":22.6364974246,
       "dewpoint":20.8834846085,
       "dewpoint_min":20.7016167413,       
       "dewpoint_min_time":"2021-05-01T05:21:45",
       "dewpoint_avg":20.7663778934,
       "dewpoint_max":20.8834846085,       
       "dewpoint_max_time":"2021-05-01T05:23:55",
       "humidity":90.0,
       "humidity_min":89.0,       
       "humidity_min_time":"2021-05-01T05:20:01",
       "humidity_avg":89.2185430464,
       "humidity_max":90.0,       
       "humidity_max_time":"2021-05-01T05:23:55",
       "barometer":1014.79893955,
       "barometer_min":1014.73121179,       
       "barometer_min_time":"2021-05-01T05:20:01",
       "barometer_avg":1014.77830725,
       "barometer_max":1014.79893955,       
       "barometer_max_time":"2021-05-01T05:21:01",
       "pressure":978.765480194,
       "pressure_avg":978.743195304,
       "wind_avg":11.2654360001,
       "wind_dir":112.5,
       "windgust":25.7495680002,
       "windgust_dir":112.5,
       "wind_max":25.7495680002,
       "wind_max_dir":117.0,        
       "wind_max_time":"2021-05-01T05:20:33",    
       "wind10_avg":11.9049120266,
       "rain":0.0,
       "rain_rate":0.0,
       "rain_rate_max_time":"2021-05-01T05:20:01", 
       "radiation_min":0.0,
       "radiation_min_time":"2021-05-01T05:20:01",
       "radiation":0.0,
       "radiation_max":0.0,
       "radiation_max_time":"2021-05-01T05:20:01",
       "in_temp":26.1111111111,
       "in_temp_max":26.1111111111,
       "in_temp_max_time":"2021-05-01T05:20:01",
       "in_temp_avg":26.1111111111,
       "in_temp_min":26.1111111111,
       "in_temp_min_time":"2021-05-01T05:20:01",
       "in_humidity":69.0,
       "in_humidity_max":69.0,
       "in_humidity_max_time":"2021-05-01T05:20:01",
       "in_humidity_avg":69.0,
       "in_humidity_min":69.0,
       "in_humidity_min_time":"2021-05-01T05:20:01",
       "rx":99.0833333333,
       "voltage":4.59,
       "duration":5.0
       }
     }
   ]
}
]
