[
{
  "meteor" : "MTG320",
  "version":2,
  "info" : {
     "title":"JSON pour BDClimato",
     "hardware":"Vantage Pro2",
     "weewxVersion":"3.9.1-1",
     "time":"17/01/2022 à 02h50",
     "uptime":"9 jours, 17 heures, 8 minutes",
     "last_update":"2022-01-17 02:50:00",
     "last_update_before_stop":"2022-01-07 09:40:00" 
     },
  "data":
     [
      {
       "start_dat":"2022-01-17T02:45:00",
       "stop_dat":"2022-01-17T02:50:00",
       "current": {
       "out_temp":23.8888888889,
       "out_temp_min":23.8333333333,       
       "out_temp_min_time":"2022-01-17T02:45:02",
       "out_temp_avg":23.8498896247,
       "out_temp_max":23.8888888889,       
       "out_temp_max_time":"2022-01-17T02:45:08",
       "windchill":23.8888888889,
       "windchill_min":23.8333333333,       
       "windchill_min_time":"2022-01-17T02:45:02",
       "windchill_avg":23.8498896247,
       "heatindex":23.8888888889,
       "heatindex_max":23.8888888889,       
       "heatindex_max_time":"2022-01-17T02:45:08",
       "heatindex_avg":23.8498896247,
       "dewpoint":23.0366517592,
       "dewpoint_min":22.9814575676,       
       "dewpoint_min_time":"2022-01-17T02:45:02",
       "dewpoint_avg":22.9979061677,
       "dewpoint_max":23.0366517592,       
       "dewpoint_max_time":"2022-01-17T02:45:08",
       "humidity":95.0,
       "humidity_min":95.0,       
       "humidity_min_time":"2022-01-17T02:45:02",
       "humidity_avg":95.0,
       "humidity_max":95.0,       
       "humidity_max_time":"2022-01-17T02:45:02",
       "barometer":1008.94048804,
       "barometer_min":1008.94048804,       
       "barometer_min_time":"2022-01-17T02:46:00",
       "barometer_avg":1008.96089607,
       "barometer_max":1009.04207968,       
       "barometer_max_time":"2022-01-17T02:45:02",
       "pressure":973.483124203,
       "pressure_min":973.481890714,       
       "pressure_min_time":"2022-01-17T02:46:20",
       "pressure_avg":973.501949127,
       "pressure_max":973.581145596,       
       "pressure_max_time":"2022-01-17T02:45:08",
       "wind_avg":0.894082222943,
       "wind_dir":135.0,
       "wind_max":1.34112333441,
       "wind_max_dir":135.0,
       "wind_max_time":"2022-01-17T02:45:02",    
       "wind10_avg":1.69638779386,
       "rain":0.0,
       "rain_rate_max":0.0,
       "rain_rate_max_time":"2022-01-17T02:45:02", 
       "rain_rate_avg":0.0,
       "in_temp":28.7777777778,
       "in_temp_max":28.7777777778,
       "in_temp_max_time":"2022-01-17T02:45:02",
       "in_temp_avg":28.7777777778,
       "in_temp_min":28.7777777778,
       "in_temp_min_time":"2022-01-17T02:45:02",
       "in_humidity":76.0,
       "in_humidity_max":76.0,
       "in_humidity_max_time":"2022-01-17T02:45:02",
       "in_humidity_avg":76.0,
       "in_humidity_min":76.0,
       "in_humidity_min_time":"2022-01-17T02:45:02",
       "rx":99.9375,
       "voltage":4.58,
       "voltage_avg":4.58,
       "voltage_min":4.58,
       "voltage_min_time":"2022-01-17T02:45:02",
       "duration":5.0
       }
     }
   ]
}
]
