[
{
  "meteor" : "MTG320",
  "version":2,
  "info" : {
     "title":"JSON pour BDClimato",
     "hardware":"Vantage Pro2",
     "weewxVersion":"3.9.2",
     "time":"27/12/2021 à 21h05",
     "uptime":"7 jours, 13 heures, 12 minutes",
     "last_update":"2021-12-27 21:05:00",
     "last_update_before_stop":"2021-12-20 07:10:00" 
     },
  "data":
     [
      {
       "start_dat":"2021-12-27T21:00:00",
       "stop_dat":"2021-12-27T21:05:00",
       "current": {
       "out_temp":22.5555555556,
       "out_temp_min":22.5,       
       "out_temp_min_time":"2021-12-27T21:00:03",
       "out_temp_avg":22.5055555556,
       "out_temp_max":22.5555555556,       
       "out_temp_max_time":"2021-12-27T21:01:46",
       "windchill":22.5555555556,
       "windchill_min":22.5,       
       "windchill_min_time":"2021-12-27T21:00:03",
       "windchill_avg":22.5055555556,
       "heatindex":22.5555555556,
       "heatindex_max":22.5555555556,       
       "heatindex_max_time":"2021-12-27T21:01:46",
       "heatindex_avg":22.5055555556,
       "dewpoint":21.3636379932,
       "dewpoint_min":21.3085900849,       
       "dewpoint_min_time":"2021-12-27T21:00:03",
       "dewpoint_avg":21.3140948757,
       "dewpoint_max":21.3636379932,       
       "dewpoint_max_time":"2021-12-27T21:01:46",
       "humidity":93.0,
       "humidity_min":93.0,       
       "humidity_min_time":"2021-12-27T21:00:03",
       "humidity_avg":93.0,
       "humidity_max":93.0,       
       "humidity_max_time":"2021-12-27T21:00:03",
       "barometer":1015.27303389,
       "barometer_min":1015.23917001,       
       "barometer_min_time":"2021-12-27T21:00:04",
       "barometer_avg":1015.30035076,
       "barometer_max":1015.34076166,       
       "barometer_max_time":"2021-12-27T21:01:02",
       "pressure":979.298033162,
       "pressure_min":979.264218081,       
       "pressure_min_time":"2021-12-27T21:00:04",
       "pressure_avg":979.323346012,
       "pressure_max":979.363361072,       
       "pressure_max_time":"2021-12-27T21:01:46",
       "wind_avg":1.34112333441,
       "wind_dir":157.5,
       "wind_max":3.1292877803,
       "wind_max_dir":157.5,
       "wind_max_time":"2021-12-27T21:00:03",    
       "wind10_avg":1.34112333441,
       "rain":0.0,
       "rain_rate_max":0.0,
       "rain_rate_max_time":"2021-12-27T21:00:03", 
       "rain_rate_avg":0.0,
       "in_temp":27.5,
       "in_temp_max":27.5,
       "in_temp_max_time":"2021-12-27T21:00:03",
       "in_temp_avg":27.5,
       "in_temp_min":27.5,
       "in_temp_min_time":"2021-12-27T21:00:03",
       "in_humidity":69.0,
       "in_humidity_max":69.0,
       "in_humidity_max_time":"2021-12-27T21:00:03",
       "in_humidity_avg":69.0,
       "in_humidity_min":69.0,
       "in_humidity_min_time":"2021-12-27T21:00:03",
       "rx":99.9375,
       "voltage":4.58,
       "voltage_avg":4.58,
       "voltage_min":4.58,
       "voltage_min_time":"2021-12-27T21:00:03",
       "duration":5.0
       }
     }
   ]
}
]
