[
{
  "meteor" : "MTG320",
  "version":2,
  "info" : {
     "title":"JSON pour BDClimato",
     "hardware":"Vantage Pro2",
     "weewxVersion":"3.9.1-1",
     "time":"13/01/2022 à 12h20",
     "uptime":"6 jours, 2 heures, 38 minutes",
     "last_update":"2022-01-13 12:20:00",
     "last_update_before_stop":"2022-01-07 09:40:00" 
     },
  "data":
     [
      {
       "start_dat":"2022-01-13T12:15:00",
       "stop_dat":"2022-01-13T12:20:00",
       "current": {
       "out_temp":26.7222222222,
       "out_temp_min":26.5555555556,       
       "out_temp_min_time":"2022-01-13T12:15:02",
       "out_temp_avg":26.6545253863,
       "out_temp_max":26.7222222222,       
       "out_temp_max_time":"2022-01-13T12:19:10",
       "windchill":26.7222222222,
       "windchill_min":26.5555555556,       
       "windchill_min_time":"2022-01-13T12:15:02",
       "windchill_avg":26.6545253863,
       "heatindex":29.8687626491,
       "heatindex_max":29.8687626491,       
       "heatindex_max_time":"2022-01-13T12:19:10",
       "heatindex_avg":28.755107409,
       "dewpoint":24.752166264,
       "dewpoint_min":24.6974353631,       
       "dewpoint_min_time":"2022-01-13T12:16:44",
       "dewpoint_avg":24.7500262944,
       "dewpoint_max":24.8849734232,       
       "dewpoint_max_time":"2022-01-13T12:16:36",
       "humidity":89.0,
       "humidity_min":89.0,       
       "humidity_min_time":"2022-01-13T12:16:44",
       "humidity_avg":89.3443708609,
       "humidity_max":90.0,       
       "humidity_max_time":"2022-01-13T12:15:02",
       "barometer":1013.17347324,
       "barometer_min":1013.00415383,       
       "barometer_min_time":"2022-01-13T12:15:02",
       "barometer_avg":1013.13983362,
       "barometer_max":1013.17347324,       
       "barometer_max_time":"2022-01-13T12:16:00",
       "pressure":977.479486233,
       "pressure_min":977.316696151,       
       "pressure_min_time":"2022-01-13T12:15:02",
       "pressure_avg":977.446977701,
       "pressure_max":977.482771529,       
       "pressure_max_time":"2022-01-13T12:16:36",
       "wind_avg":2.23520555736,
       "wind_dir":90.0,
       "wind_max":5.36449333766,
       "wind_max_dir":90.0,
       "wind_max_time":"2022-01-13T12:15:02",    
       "wind10_avg":2.50165390194,
       "rain":0.0,
       "rain_rate_max":0.0,
       "rain_rate_max_time":"2022-01-13T12:15:02", 
       "rain_rate_avg":0.0,
       "in_temp":27.5,
       "in_temp_max":27.5555555556,
       "in_temp_max_time":"2022-01-13T12:16:00",
       "in_temp_avg":27.5224429728,
       "in_temp_min":27.5,
       "in_temp_min_time":"2022-01-13T12:15:02",
       "in_humidity":74.0,
       "in_humidity_max":74.0,
       "in_humidity_max_time":"2022-01-13T12:18:00",
       "in_humidity_avg":73.4039735099,
       "in_humidity_min":73.0,
       "in_humidity_min_time":"2022-01-13T12:15:02",
       "rx":97.375,
       "voltage":4.58,
       "voltage_avg":4.58,
       "voltage_min":4.58,
       "voltage_min_time":"2022-01-13T12:15:02",
       "duration":5.0
       }
     }
   ]
}
]
