[
{
  "meteor" : "MTG320",
  "version":2,
  "info" : {
     "title":"JSON pour BDClimato",
     "time":"28/04/2021 à 13h05",
     "uptime":"2 jours, 1 heure, 4 minutes",
     "last_update":"2021-04-28 13:05:00",
     "last_update_before_stop":"2021-04-26 11:45:00" 
     },
  "data":
     [
      {
       "start_dat":"2021-04-28T13:00:00",
       "stop_dat":"2021-04-28T13:05:00",
       "current": {
       "out_temp":26.5,
       "out_temp_min":26.5555555556,       
       "out_temp_min_time":"2021-04-28T13:03:19",
       "out_temp_avg":26.6887417219,
       "out_temp_max":26.8888888889,       
       "out_temp_max_time":"2021-04-28T13:00:01",
       "windchill":26.5,
       "windchill_min":26.5555555556,       
       "windchill_min_time":"2021-04-28T13:03:19",
       "windchill_avg":26.6887417219,
       "heatindex":26.5,
       "heatindex_max":29.322563016,       
       "heatindex_max_time":"2021-04-28T13:00:31",
       "heatindex_avg":27.9707070153,
       "dewpoint":22.7594475431,
       "dewpoint_min":22.4493655119,       
       "dewpoint_min_time":"2021-04-28T13:02:47",
       "dewpoint_avg":22.6267445218,
       "dewpoint_max":22.8134409592,       
       "dewpoint_max_time":"2021-04-28T13:03:57",
       "humidity":80.0,
       "humidity_min":77.0,       
       "humidity_min_time":"2021-04-28T13:00:01",
       "humidity_avg":78.4900662252,
       "humidity_max":80.0,       
       "humidity_max_time":"2021-04-28T13:03:57",
       "barometer":1015.57780883,
       "barometer_min":1015.40848942,       
       "barometer_min_time":"2021-04-28T13:00:03",
       "barometer_avg":1015.51703325,
       "barometer_max":1015.64553659,       
       "barometer_max_time":"2021-04-28T13:03:01",
       "pressure":979.687458379,
       "pressure_avg":979.62588191,
       "wind_avg":14.4841320001,
       "wind_dir":90.0,
       "windgust":35.4056560002,
       "windgust_dir":90.0,
       "wind_max":35.4056560002,
       "wind_max_dir":153.0,        
       "wind_max_time":"2021-04-28T13:01:35",    
       "wind10_avg":14.8038700133,
       "rain":0.0,
       "rain_rate":0.0,
       "rain_rate_max_time":"2021-04-28T13:00:01", 
       "radiation_min":0.0821051346642,
       "radiation_min_time":"2021-04-28T13:04:59",
       "radiation":24.7114001255,
       "radiation_max":0.0826256406788,
       "radiation_max_time":"2021-04-28T13:00:01",
       "in_temp":26.4444444444,
       "in_temp_max":26.4444444444,
       "in_temp_max_time":"2021-04-28T13:00:01",
       "in_temp_avg":26.4444444444,
       "in_temp_min":26.4444444444,
       "in_temp_min_time":"2021-04-28T13:00:01",
       "in_humidity":71.0,
       "in_humidity_max":71.0,
       "in_humidity_max_time":"2021-04-28T13:00:01",
       "in_humidity_avg":71.0,
       "in_humidity_min":71.0,
       "in_humidity_min_time":"2021-04-28T13:00:01",
       "rx":99.0833333333,
       "voltage":4.59,
       "duration":5.0
       }
     }
   ]
}
]
