[
{
  "meteor" : "MTG320",
  "version":2,
  "info" : {
     "title":"JSON pour BDClimato",
     "hardware":"Vantage Pro2",
     "weewxVersion":"3.9.1-1",
     "time":"29/01/2022 à 10h45",
     "uptime":"22 jours, 1 heure, 3 minutes",
     "last_update":"2022-01-29 10:45:00",
     "last_update_before_stop":"2022-01-07 09:40:00" 
     },
  "data":
     [
      {
       "start_dat":"2022-01-29T10:40:00",
       "stop_dat":"2022-01-29T10:45:00",
       "current": {
       "out_temp":27.1111111111,
       "out_temp_min":27.0,       
       "out_temp_min_time":"2022-01-29T10:40:02",
       "out_temp_avg":27.0180279617,
       "out_temp_max":27.1111111111,       
       "out_temp_max_time":"2022-01-29T10:44:44",
       "windchill":27.1111111111,
       "windchill_min":27.0,       
       "windchill_min_time":"2022-01-29T10:40:02",
       "windchill_avg":27.0180279617,
       "heatindex":30.4000417653,
       "heatindex_max":30.4000417653,       
       "heatindex_max_time":"2022-01-29T10:44:44",
       "heatindex_avg":29.9314007328,
       "dewpoint":24.1658490904,
       "dewpoint_min":23.4515965695,       
       "dewpoint_min_time":"2022-01-29T10:40:02",
       "dewpoint_avg":23.5822142622,
       "dewpoint_max":24.1658490904,       
       "dewpoint_max_time":"2022-01-29T10:44:44",
       "humidity":84.0,
       "humidity_min":81.0,       
       "humidity_min_time":"2022-01-29T10:40:02",
       "humidity_avg":81.5562913907,
       "humidity_max":84.0,       
       "humidity_max_time":"2022-01-29T10:44:41",
       "barometer":1013.10574547,
       "barometer_min":1013.10574547,       
       "barometer_min_time":"2022-01-29T10:42:00",
       "barometer_avg":1013.14611301,
       "barometer_max":1013.20733712,       
       "barometer_max_time":"2022-01-29T10:40:02",
       "pressure":977.335404836,
       "pressure_min":977.318539425,       
       "pressure_min_time":"2022-01-29T10:42:00",
       "pressure_avg":977.360542136,
       "pressure_max":977.41654242,       
       "pressure_max_time":"2022-01-29T10:40:02",
       "wind_avg":0.894082222943,
       "wind_dir":315.0,
       "wind_max":1.78816444589,
       "wind_max_dir":22.5,
       "wind_max_time":"2022-01-29T10:44:08",    
       "wind10_avg":0.447041111472,
       "rain":0.0,
       "rain_rate_max":0.0,
       "rain_rate_max_time":"2022-01-29T10:40:02", 
       "rain_rate_avg":0.0,
       "in_temp":27.3333333333,
       "in_temp_max":27.3333333333,
       "in_temp_max_time":"2022-01-29T10:41:00",
       "in_temp_avg":27.3222958057,
       "in_temp_min":27.2777777778,
       "in_temp_min_time":"2022-01-29T10:40:02",
       "in_humidity":67.0,
       "in_humidity_max":67.0,
       "in_humidity_max_time":"2022-01-29T10:40:02",
       "in_humidity_avg":67.0,
       "in_humidity_min":67.0,
       "in_humidity_min_time":"2022-01-29T10:40:02",
       "rx":99.9375,
       "voltage":4.58,
       "voltage_avg":4.58,
       "voltage_min":4.58,
       "voltage_min_time":"2022-01-29T10:40:02",
       "duration":5.0
       }
     }
   ]
}
]
